immutabledict/__init__.py
immutabledict/py.typed
immutabledict-4.1.0.dist-info/LICENSE
immutabledict-4.1.0.dist-info/METADATA
immutabledict-4.1.0.dist-info/WHEEL
immutabledict-4.1.0.dist-info/RECORD
