Metadata-Version: 2.1
Name: immutabledict
Version: 4.1.0
Summary: Immutable wrapper around dictionaries (a fork of frozendict)
Home-page: https://github.com/corenting/immutabledict
License: MIT
Keywords: immutable,dictionary
Author: Corentin Garcia
Author-email: corenting@gmail.com
Requires-Python: >=3.8,<4.0
Classifier: Development Status :: 5 - Production/Stable
Classifier: License :: OSI Approved :: MIT License
Classifier: Programming Language :: Python :: 3
Classifier: Programming Language :: Python :: 3.8
Classifier: Programming Language :: Python :: 3.9
Classifier: Programming Language :: Python :: 3.10
Classifier: Programming Language :: Python :: 3.11
Classifier: Programming Language :: Python :: 3.12
Classifier: Topic :: Software Development :: Libraries :: Python Modules
Project-URL: Bug Tracker, https://github.com/corenting/immutabledict/issues
Project-URL: Changelog, https://github.com/corenting/immutabledict/blob/master/CHANGELOG.md
Project-URL: Documentation, https://immutabledict.corenting.fr
Project-URL: Donation, https://corenting.fr/donate
Project-URL: Repository, https://github.com/corenting/immutabledict
